shenmind/__init__.py
shenmind/constant.py
shenmind/shenmind.py
shenmind/upload.py
shenmind-2.0.0.dist-info/LICENSE
shenmind-2.0.0.dist-info/METADATA
shenmind-2.0.0.dist-info/WHEEL
shenmind-2.0.0.dist-info/top_level.txt
shenmind-2.0.0.dist-info/RECORD
